[
    {
        "threadID": "6333508226666909",
        "listRule": []
    },
    {
        "threadID": "4563174340369177",
        "listRule": [
            "Dùng lệnh 18+ ban ngày ban nhé",
            "add bot tắt rankup+resend+nickname"
        ]
    },
    {
        "threadID": "4728656460579493",
        "listRule": [
            "Hoàng Nguyên đẹp trai",
            "nguyên cute"
        ]
    },
    {
        "threadID": "7443397572399390",
        "listRule": [
            "Đổi tên game thành MFAメ tên khi vào (Box có thể thông cảm cho vài ngày để cày kim cuơng nếu chưa đủ)",
            "Đổi biệt danh trong box thành MFAメ tên + năm sinh",
            "Không phân biệt, kì thị tuổi tác, giới tính, giàu nghèo",
            "Không war trong box muốn thì tự ib riêng",
            "Tôn trọng tất cả mọi ngưòi",
            "Xin vào đựoc thì xin ra đuợc (out chửi)",
            "Vui vẻ, hòa đồng, thân thiện",
            "Biết điều, không trẻ trâu, kiếm chuyện",
            "Có chụp hình và giao lưu, nếu bận không tham gia đuợc thì báo quản trị viên họăc boss",
            "LÀM SAI NHẮC NHỞ QUÁ 3 LẦN KICK ✨Mong làm đúng theo luật✨"
        ]
    }
]